v_vk_api/__init__.py
v_vk_api/api.py
v_vk_api/exceptions.py
v_vk_api/session.py
v_vk_api/t1.py
v_vk_api/utils.py
v_vk_api-1.3.dist-info/LICENSE.txt
v_vk_api-1.3.dist-info/METADATA
v_vk_api-1.3.dist-info/RECORD
v_vk_api-1.3.dist-info/WHEEL
v_vk_api-1.3.dist-info/top_level.txt
