Metadata-Version: 2.1
Name: v-vk-api
Version: 1.3
Summary: VK API wrapper
Home-page: https://github.com/vadimk2016/v-vk-api
Author: Vadim Kuznetsov
Author-email: vadim.kuznyetsov@gmail.com
License: MIT
Keywords: v-vk-api
Platform: UNKNOWN
Classifier: Development Status :: 5 - Production/Stable
Classifier: Intended Audience :: Developers
Classifier: License :: OSI Approved :: MIT License
Classifier: Operating System :: Microsoft
Classifier: Operating System :: Unix
Classifier: Programming Language :: Python :: 3
Classifier: Topic :: Internet
Requires-Python: >=3
Requires-Dist: beautifulsoup4 (==4.6.0)
Requires-Dist: certifi (==2018.4.16)
Requires-Dist: chardet (==3.0.4)
Requires-Dist: idna (==2.6)
Requires-Dist: requests (==2.18.4)
Requires-Dist: urllib3 (==1.22)
